[
  {
    "name": "chili tomato",
    "id": 364,
    "category": "Fruit"
  },
  {
    "name": "cocktail mix margarita",
    "id": 375,
    "category": "Fruit"
  },
  {
    "name": "cuervo margarita mix",
    "id": 863,
    "category": "Fruit"
  },
  {
    "name": "delmonte tomato",
    "id": 446,
    "category": "Fruit"
  },
  {
    "name": "eggplant caponata",
    "id": 387,
    "category": "Fruit"
  },
  {
    "name": "fort guacamole",
    "id": 165,
    "category": "Fruit"
  },
  {
    "name": "fruit peach",
    "id": 201,
    "category": "Fruit"
  },
  {
    "name": "chili paste bean",
    "id": 284,
    "category": "Vegetable"
  },
  {
    "name": "chinese",
    "id": 353,
    "category": "Vegetable"
  },
  {
    "name": "chunk white onion",
    "id": 348,
    "category": "Vegetable"
  },
  {
    "name": "clearjel starch",
    "id": 373,
    "category": "Vegetable"
  },
  {
    "name": "rosemary",
    "id": 264,
    "category": "Herbs and Spices"
  },
  {
    "name": "chive",
    "id": 343,
    "category": "Herbs and Spices"
  },
  {
    "name": "savory",
    "id": 444,
    "category": "Herbs and Spices"
  },
  {
    "name": "galangal",
    "id": 333,
    "category": "Herbs and Spices"
  },
  {
    "name": "sea salt black pepper",
    "id": 363,
    "category": "Herbs and Spices"
  },
  {
    "name": "rocket",
    "id": 423,
    "category": "Herbs and Spices"
  },
  {
    "name": "spearmint",
    "id": 262,
    "category": "Herbs and Spices"
  },
  {
    "name": "couscous",
    "id": 864,
    "category": "Cereal"
  },
  {
    "name": "tortilla",
    "id": 835,
    "category": "Cereal"
  },
  {
    "name": "tahini",
    "id": 299,
    "category": "Cereal"
  },
  {
    "name": "quinoa",
    "id": 616,
    "category": "Cereal"
  },
  {
    "name": "yellow cake mix",
    "id": 768,
    "category": "Cereal"
  },
  {
    "name": "cellophane noodle",
    "id": 484,
    "category": "Cereal"
  },
  {
    "name": "mexican rice",
    "id": 55,
    "category": "Cereal"
  },
  {
    "name": "sambal oelek",
    "id": 833,
    "category": "Fish"
  },
  {
    "name": "sambal chili paste",
    "id": 777,
    "category": "Fish"
  },
  {
    "name": "pepper oil sambal oelek",
    "id": 339,
    "category": "Fish"
  },
  {
    "name": "chuck blade roast",
    "id": 276,
    "category": "Meat"
  },
  {
    "name": "cranberry jell o gelatin",
    "id": 229,
    "category": "Meat"
  },
  {
    "name": "dozen tamale",
    "id": 270,
    "category": "Meat"
  },
  {
    "name": "fryer rabbit",
    "id": 617,
    "category": "Meat"
  },
  {
    "name": "green jell o",
    "id": 241,
    "category": "Meat"
  },
  {
    "name": "bisquick baking mix",
    "id": 1,
    "category": "Bakery"
  },
  {
    "name": "bisquick heart smart mix",
    "id": 485,
    "category": "Bakery"
  },
  {
    "name": "bisquick mix",
    "id": 857,
    "category": "Bakery"
  },
  {
    "name": "chocolate cookie crumb vanilla",
    "id": 245,
    "category": "Dairy"
  },
  {
    "name": "chocolate cream",
    "id": 763,
    "category": "Dairy"
  },
  {
    "name": "cream anything soup mix",
    "id": 89,
    "category": "Dairy"
  },
  {
    "name": "thyme honey",
    "id": 269,
    "category": "Plant"
  },
  {
    "name": "haddock fillet",
    "id": 566,
    "category": "Seafood"
  },
  {
    "name": "sardine",
    "id": 635,
    "category": "Seafood"
  },
  {
    "name": "ice",
    "id": 794,
    "category": "Beverage"
  },
  {
    "name": "coffee",
    "id": 46,
    "category": "Beverage"
  },
  {
    "name": "wine",
    "id": 32,
    "category": "Beverage"
  },
  {
    "name": "gin",
    "id": 23,
    "category": "Beverage"
  },
  {
    "name": "champagne",
    "id": 35,
    "category": "Beverage"
  },
  {
    "name": "black tea",
    "id": 48,
    "category": "Beverage"
  },
  {
    "name": "pomegranate juice",
    "id": 394,
    "category": "Beverage"
  },
  {
    "name": "chambord raspberry liquor",
    "id": 233,
    "category": "Beverage"
  }
]